README.txt
setup.py
RequestDumpster.egg-info/PKG-INFO
RequestDumpster.egg-info/SOURCES.txt
RequestDumpster.egg-info/dependency_links.txt
RequestDumpster.egg-info/entry_points.txt
RequestDumpster.egg-info/not-zip-safe
RequestDumpster.egg-info/requires.txt
RequestDumpster.egg-info/top_level.txt
requestdumpster/__init__.py
requestdumpster/dumpster.py