Metadata-Version: 1.0
Name: RequestDumpster
Version: 0.2
Summary: dump requests
Home-page: http://k0s.org/hg/RequestDumpster
Author: Jeff Hammel
Author-email: k0scist@gmail.com
License: UNKNOWN
Platform: UNKNOWN
